pyvban/__init__.py
pyvban/const.py
pyvban/packet.py
pyvban/subprotocols/__init__.py
pyvban/subprotocols/audio/__init__.py
pyvban/subprotocols/audio/const.py
pyvban/subprotocols/audio/header.py
pyvban/subprotocols/serial/__init__.py
pyvban/subprotocols/serial/const.py
pyvban/subprotocols/serial/header.py
pyvban/subprotocols/text/__init__.py
pyvban/subprotocols/text/const.py
pyvban/subprotocols/text/header.py
pyvban/utils/__init__.py
pyvban/utils/device_list.py
pyvban/utils/receiver.py
pyvban/utils/send_text.py
pyvban/utils/sender.py
pyvban-0.1.1.dist-info/LICENSE.md
pyvban-0.1.1.dist-info/METADATA
pyvban-0.1.1.dist-info/WHEEL
pyvban-0.1.1.dist-info/RECORD
