Metadata-Version: 2.1
Name: pyVBAN
Version: 0.1.1
Summary: Python implementation of the VBAN (VB-Audio Network) protocol
Author: Samuel
Author-email: samuel@thestaticturtle.fr
Requires-Python: >=3.10,<4.0
Classifier: Programming Language :: Python :: 3
Classifier: Programming Language :: Python :: 3.10
Classifier: Programming Language :: Python :: 3.11
Classifier: Programming Language :: Python :: 3.12
Requires-Dist: pyaudio (>=0.2.14,<0.3.0)
